chappie/__init__.py
chappie/ai/__init__.py
chappie/ai/bot.py
chappie/ai/model.py
chappie/ai/search.py
chappie/skills/__init__.py
chappie/skills/chess/__init__.py
chappie/skills/chess/game_interface.py
chappie/skills/chess/game_plumbing.py
chappie/tools/__init__.py
chappie/tools/toolbox.py
chappie_ai-0.0.1.dist-info/LICENSE
chappie_ai-0.0.1.dist-info/METADATA
chappie_ai-0.0.1.dist-info/WHEEL
chappie_ai-0.0.1.dist-info/top_level.txt
chappie_ai-0.0.1.dist-info/RECORD
