Metadata-Version: 2.1
Name: chappie-ai
Version: 0.0.1
Summary: Machine learning agent
Home-page: https://github.com/bellerb/chappie.ai
Author: Ben Bellerose
Author-email: benbellerose@gmail.com
License: MIT
Keywords: python,Chappie,MuZero,RETRO
Platform: Any
Classifier: Development Status :: 3 - Alpha
Classifier: Intended Audience :: Education
Classifier: Programming Language :: Python :: 3
Classifier: Operating System :: MacOS :: MacOS X
Classifier: Operating System :: Microsoft :: Windows
Requires-Dist: torch
Requires-Dist: pandas
Requires-Dist: numpy
Requires-Dist: tdqm
Requires-Dist: einops
